odoo10_addon_l10n_br_crm_zip-10.0.1.0.0-py2.7-nspkg.pth
odoo10_addon_l10n_br_crm_zip-10.0.1.0.0.dist-info/top_level.txt
odoo10_addon_l10n_br_crm_zip-10.0.1.0.0.dist-info/WHEEL
odoo10_addon_l10n_br_crm_zip-10.0.1.0.0.dist-info/RECORD
odoo10_addon_l10n_br_crm_zip-10.0.1.0.0.dist-info/metadata.json
odoo10_addon_l10n_br_crm_zip-10.0.1.0.0.dist-info/DESCRIPTION.rst
odoo10_addon_l10n_br_crm_zip-10.0.1.0.0.dist-info/METADATA
odoo10_addon_l10n_br_crm_zip-10.0.1.0.0.dist-info/namespace_packages.txt
odoo/addons/l10n_br_crm_zip/__manifest__.py
odoo/addons/l10n_br_crm_zip/__init__.py
odoo/addons/l10n_br_crm_zip/README.rst
odoo/addons/l10n_br_crm_zip/models/__init__.py
odoo/addons/l10n_br_crm_zip/models/crm_lead.py
odoo/addons/l10n_br_crm_zip/i18n/pt_BR.po
odoo/addons/l10n_br_crm_zip/test/crm_lead_zip.yml
odoo/addons/l10n_br_crm_zip/views/crm_lead_view.xml
odoo/addons/l10n_br_crm_zip/views/crm_opportunity_view.xml
