Metadata-Version: 2.0
Name: odoo10-addon-l10n-br-crm-zip
Version: 10.0.1.0.0
Summary: Brazilian Localization CRM Zip
Home-page: http://odoobrasil.org
Author: Fabio Negrini, Odoo Community Association (OCA)
Author-email: support@odoo-community.org
License: AGPL-3
Platform: UNKNOWN
Requires-Dist: odoo (<10.1dev,>=10.0)
Requires-Dist: odoo10-addon-l10n-br-crm
Requires-Dist: odoo10-addon-l10n-br-zip
Classifier: Programming Language :: Python :: 2.7
Classifier: Framework :: Odoo
Classifier: License :: OSI Approved :: GNU Affero General Public License v3
